{"index.md":"CUDDdIKB","man_advection.md":"BP4-3tzN","man_authors.md":"fNGp6gXr","man_backend.md":"BICa7v1S","man_blankenbach.md":"w3lv1DC5","man_boundary_conditions.md":"BbFvj1lE","man_checkpointing.md":"CjZQO_d0","man_code_of_conduct.md":"zknwaKvo","man_constitutive_equations.md":"BZs6Ex94","man_contributing.md":"CZGsIDiI","man_equations.md":"CeUqqTWb","man_equations_apt.md":"C7JHFlkg","man_equations_basic.md":"BEtHWZne","man_equations_discretization.md":"B_Y6roOg","man_equations_discretization0.md":"Bq4uHhPc","man_geoparams.md":"By9Qcio6","man_installation.md":"xuwlMdsm","man_justpic.md":"E-nrbr7y","man_license.md":"DTqojjVs","man_listfunctions.md":"BHUXvIl6","man_material_physics.md":"wQe8z1xW","man_plume3d_plume3d.md":"DhL9GWZM","man_plume3d_rheology.md":"B2dKfUt2","man_restart.md":"Cnw8cdTq","man_security.md":"O8HTSPkF","man_shearbands.md":"CXD007b7","man_subduction2d_rheology.md":"DrlChPMd","man_subduction2d_setup.md":"Cdh2Vgry","man_subduction2d_subduction2d.md":"59RHUsEO"}
